<?xml version='1.0' encoding='UTF-8'?>
<BuildingA>


    <region2>
        <node id='0x001234110x00020000' name='樓梯' region='region2' lat='23.69811007026142' lon='120.52725700409886' neighbor1='0x001234120x00020000' neighbor2='' neighbor3='' neighbor4='' category='舊大樓二樓' nodeType='2' connectPointID='2' groupID='' mainID='' attachID1='12' attachID2='13' elevation='2'/>
		<node id='0x001234120x00020000' name='神經部檢查室/心臟血管功能檢查室岔路' region='region2' lat='23.697935616644298' lon='120.52725700409886' neighbor1='0x001234150x00020000' neighbor2='0x001234110x00020000' neighbor3='0x001234130x00020000' neighbor4='' neighbor5='' category='舊大樓二樓' nodeType='' connectPointID='' groupID='' mainID='' elevation='2'/>
		<node id='0x001234130x00020000' name='神經部檢查室' region='region2' lat='23.697935616644298' lon='120.527160861' neighbor1='0x001234140x00020000' neighbor2='0x001234120x00020000' neighbor3='0x000046100x00020000' neighbor4='' category='舊大樓二樓' nodeType='' connectPointID='' groupID='' mainID='' elevation='2'/>
		<node id='0x001234140x00020000' name='內視鏡/一般超音波檢查室' region='region2' lat='23.697915616644298' lon='120.527160861' neighbor1='0x001234130x00020000' neighbor2='' neighbor3='' neighbor4='' category='舊大樓二樓' nodeType='2' connectPointID='4' groupID='' mainID='' elevation='2'/>
		<node id='0x001234150x00020000' name='心臟血管功能檢查室' region='region2' lat='23.697935616644298' lon='120.527357418' neighbor1='0x001234120x00020000' neighbor2='0x001234160x00020000' neighbor3='0x123456780x175df042' neighbor4='' category='舊大樓二樓' nodeType='' connectPointID='' groupID='' mainID='' elevation='2'/>
		<node id='0x001234160x00020000' name='迴轉樓梯' region='region2' lat='23.697915616644298' lon='120.527357418' neighbor1='0x001234150x00020000' neighbor2='' neighbor3='' neighbor4='' category='舊大樓二樓' nodeType='2' connectPointID='3' groupID='' mainID='' elevation='2'/>
		<node id='0x123456780x175df042' name='心臟血管右邊虛設點' region='region2' lat='23.697935616644298' lon='120.531357418' neighbor1='0x001234150x00020000' neighbor2='' neighbor3='' neighbor4='' category='舊大樓二樓' nodeType='' connectPointID='' groupID='' mainID='' elevation='2'/>
		<node id='0x000046100x00020000' name='神經部檢查室左邊虛設點' region='region2' lat='23.697935616644298' lon='120.525160861' neighbor1='0x001234130x00020000' neighbor2='' neighbor3='' neighbor4='' category='舊大樓二樓' nodeType='' connectPointID='' groupID='' mainID='' elevation='2'/>
    </region2>




</BuildingA>


